DOCUMENT.rst
MANIFEST.in
README.md
requirements.txt
setup.cfg
setup.py
godEyes/__init__.py
godEyes/globalVal.py
godEyes.egg-info/PKG-INFO
godEyes.egg-info/SOURCES.txt
godEyes.egg-info/dependency_links.txt
godEyes.egg-info/top_level.txt