Metadata-Version: 1.1
Name: godEyes
Version: 1.0.6
Summary: usertrack auto test framework
Home-page: UNKNOWN
Author: shenlang
Author-email: shenlang@alibaba-inc.com
License: Apache 2.0
Keywords: usertrack app test testframework godEyes ic
Platform: UNKNOWN
Classifier: Development Status :: 3 - Alpha
Classifier: Intended Audience :: Developers
Classifier: Topic :: Software Development :: Build Tools
Classifier: License :: OSI Approved :: Apache Software License
Classifier: Programming Language :: Python :: 2
Classifier: Programming Language :: Python :: 2.6
Classifier: Programming Language :: Python :: 2.7
Classifier: Programming Language :: Python :: 3
Classifier: Programming Language :: Python :: 3.3
Classifier: Programming Language :: Python :: 3.4
Classifier: Programming Language :: Python :: 3.5
